simple_package_11/__init__.py
simple_package_11/sp1/__init__.py
simple_package_11/sp1/a.py
simple_package_11/sp2/__init__.py
simple_package_11/sp2/b.py
simple_package_11-0.0.1.dist-info/METADATA
simple_package_11-0.0.1.dist-info/WHEEL
simple_package_11-0.0.1.dist-info/top_level.txt
simple_package_11-0.0.1.dist-info/RECORD
