Metadata-Version: 2.1
Name: simple-package-11
Version: 0.0.1
Summary: summy package
Home-page: UNKNOWN
Author: UNKNOWN
Author-email: UNKNOWN
License: UNKNOWN
Platform: UNKNOWN
